README.md
setup.py
ETL/__init__.py
ETL/module1_name/Projeto.py
ETL/module1_name/__init__.py
Projeto_ETL.egg-info/PKG-INFO
Projeto_ETL.egg-info/SOURCES.txt
Projeto_ETL.egg-info/dependency_links.txt
Projeto_ETL.egg-info/top_level.txt