Metadata-Version: 2.1
Name: Projeto-ETL
Version: 0.0.1
Summary: Extração e tratamento de dados via Python
Home-page: UNKNOWN
Author: Cesar Szabo
License: UNKNOWN
Platform: UNKNOWN
